{
  "Adjetivos": [
    {
      "word": "Alegre",
      "image": "image/Adjetivos/Alegre.png"
    },
    {
      "word": "Amable",
      "image": "image/Adjetivos/Amable.png"
    },
    {
      "word": "Aventurero",
      "image": "image/Adjetivos/Aventurero.png"
    },
    {
      "word": "Caliente",
      "image": "image/Adjetivos/Caliente.png"
    },
    {
      "word": "Enérgico",
      "image": "image/Adjetivos/Enérgico.png"
    },
    {
      "word": "Frío",
      "image": "image/Adjetivos/Frío.png"
    },
    {
      "word": "Inteligente",
      "image": "image/Adjetivos/Inteligente.png"
    },
    {
      "word": "Limpio",
      "image": "image/Adjetivos/Limpio.png"
    },
    {
      "word": "Nervioso",
      "image": "image/Adjetivos/Nervioso.png"
    },
    {
      "word": "Ruidoso",
      "image": "image/Adjetivos/Ruidoso.png"
    },
    {
      "word": "Tranquilo",
      "image": "image/Adjetivos/Tranquilo.png"
    }
  ],
  "Animales_de_compañía": [
    {
      "word": "El conejo",
      "image": "image/Animales_de_compañía/El_conejo.png"
    },
    {
      "word": "El gato",
      "image": "image/Animales_de_compañía/El_gato.png"
    },
    {
      "word": "El hurón",
      "image": "image/Animales_de_compañía/El_hurón.png"
    },
    {
      "word": "El hámster",
      "image": "image/Animales_de_compañía/El_hámster.png"
    },
    {
      "word": "El loro",
      "image": "image/Animales_de_compañía/El_loro.png"
    },
    {
      "word": "El periquito",
      "image": "image/Animales_de_compañía/El_periquito.png"
    },
    {
      "word": "El perro",
      "image": "image/Animales_de_compañía/El_perro.png"
    },
    {
      "word": "El pez rojo",
      "image": "image/Animales_de_compañía/El_pez_rojo.png"
    },
    {
      "word": "El pájaro",
      "image": "image/Animales_de_compañía/El_pájaro.png"
    },
    {
      "word": "La iguana",
      "image": "image/Animales_de_compañía/La_iguana.png"
    },
    {
      "word": "La serpiente",
      "image": "image/Animales_de_compañía/La_serpiente.png"
    },
    {
      "word": "La tortuga",
      "image": "image/Animales_de_compañía/La_tortuga.png"
    }
  ],
  "Animales_de_invierno": [
    {
      "word": "El búho nival",
      "image": "image/Animales_de_invierno/El_búho_nival.png"
    },
    {
      "word": "El caribú",
      "image": "image/Animales_de_invierno/El_caribú.png"
    },
    {
      "word": "El leopardo de las nieves",
      "image": "image/Animales_de_invierno/El_leopardo_de_las_nieves.png"
    },
    {
      "word": "El lobo ártico",
      "image": "image/Animales_de_invierno/El_lobo_ártico.png"
    },
    {
      "word": "El narval",
      "image": "image/Animales_de_invierno/El_narval.png"
    },
    {
      "word": "El oso polar",
      "image": "image/Animales_de_invierno/El_oso_polar.png"
    },
    {
      "word": "El perro esquimal",
      "image": "image/Animales_de_invierno/El_perro_esquimal.png"
    },
    {
      "word": "El pingüino",
      "image": "image/Animales_de_invierno/El_pingüino.png"
    },
    {
      "word": "El reno",
      "image": "image/Animales_de_invierno/El_reno.png"
    },
    {
      "word": "El zorro ártico",
      "image": "image/Animales_de_invierno/El_zorro_ártico.png"
    },
    {
      "word": "La liebre ártica",
      "image": "image/Animales_de_invierno/La_liebre_ártica.png"
    },
    {
      "word": "La morsa",
      "image": "image/Animales_de_invierno/La_morsa.png"
    }
  ],
  "Descripciones_físicas": [
    {
      "word": "Alto",
      "image": "image/Descripciones_físicas/Alto.png"
    },
    {
      "word": "Bajo",
      "image": "image/Descripciones_físicas/Bajo.png"
    },
    {
      "word": "Calvo",
      "image": "image/Descripciones_físicas/Calvo.png"
    },
    {
      "word": "Corto",
      "image": "image/Descripciones_físicas/Corto.png"
    },
    {
      "word": "Delgado",
      "image": "image/Descripciones_físicas/Delgado.png"
    },
    {
      "word": "Flaco",
      "image": "image/Descripciones_físicas/Flaco.png"
    },
    {
      "word": "Gordo",
      "image": "image/Descripciones_físicas/Gordo.png"
    },
    {
      "word": "Grande",
      "image": "image/Descripciones_físicas/Grande.png"
    },
    {
      "word": "Joven",
      "image": "image/Descripciones_físicas/Joven.png"
    },
    {
      "word": "Largo",
      "image": "image/Descripciones_físicas/Largo.png"
    },
    {
      "word": "Musculoso",
      "image": "image/Descripciones_físicas/Musculoso.png"
    },
    {
      "word": "Pequeno",
      "image": "image/Descripciones_físicas/Pequeno.png"
    },
    {
      "word": "Viejo",
      "image": "image/Descripciones_físicas/Viejo.png"
    }
  ],
  "El_mar": [
    {
      "word": "El buzo",
      "image": "image/El_mar/El_buzo.png"
    },
    {
      "word": "El caballito de mar",
      "image": "image/El_mar/El_caballito_de_mar.png"
    },
    {
      "word": "El camaron",
      "image": "image/El_mar/El_camaron.png"
    },
    {
      "word": "El delfín",
      "image": "image/El_mar/El_delfín.png"
    },
    {
      "word": "El pez",
      "image": "image/El_mar/El_pez.png"
    },
    {
      "word": "El pulpo",
      "image": "image/El_mar/El_pulpo.png"
    },
    {
      "word": "El submarino",
      "image": "image/El_mar/El_submarino.png"
    },
    {
      "word": "El tiburón",
      "image": "image/El_mar/El_tiburón.png"
    },
    {
      "word": "La estrella de mar",
      "image": "image/El_mar/La_estrella_de_mar.png"
    },
    {
      "word": "La mantarraya",
      "image": "image/El_mar/La_mantarraya.png"
    },
    {
      "word": "La medusa",
      "image": "image/El_mar/La_medusa.png"
    },
    {
      "word": "La tortuga",
      "image": "image/El_mar/La_tortuga.png"
    },
    {
      "word": "Las algas marinas",
      "image": "image/El_mar/Las_algas_marinas.png"
    }
  ],
  "Emociones": [
    {
      "word": "Aburrido",
      "image": "image/Emociones/Aburrido.png"
    },
    {
      "word": "Asustado",
      "image": "image/Emociones/Asustado.png"
    },
    {
      "word": "Avergonzado",
      "image": "image/Emociones/Avergonzado.png"
    },
    {
      "word": "Cansado",
      "image": "image/Emociones/Cansado.png"
    },
    {
      "word": "Confundido",
      "image": "image/Emociones/Confundido.png"
    },
    {
      "word": "Emocionado",
      "image": "image/Emociones/Emocionado.png"
    },
    {
      "word": "Enojado",
      "image": "image/Emociones/Enojado.png"
    },
    {
      "word": "Feliz",
      "image": "image/Emociones/Feliz.png"
    },
    {
      "word": "Nervioso",
      "image": "image/Emociones/Nervioso.png"
    },
    {
      "word": "Sorprendido",
      "image": "image/Emociones/Sorprendido.png"
    },
    {
      "word": "Tranquilo",
      "image": "image/Emociones/Tranquilo.png"
    },
    {
      "word": "Triste",
      "image": "image/Emociones/Triste.png"
    }
  ],
  "Frutas": [
    {
      "word": "La manzana",
      "image": "https://static.wixstatic.com/media/8d0b81_4ccc6ce3256a4d54bf43d34a812ba016~mv2.png"
    },
    {
      "word": "El plátano",
      "image": "https://static.wixstatic.com/media/8d0b81_cfd9f750439d4aff907242f3ce8db3a0~mv2.png"
    },
    {
      "word": "La pera",
      "image": "https://static.wixstatic.com/media/8d0b81_917202cb5ead49ddb0936d3d085e4474~mv2.png"
    },
    {
      "word": "Las fresas",
      "image": "https://static.wixstatic.com/media/8d0b81_8025f02381164485abd63d7d3f893ef6~mv2.png"
    },
    {
      "word": "Los arándanos",
      "image": "https://static.wixstatic.com/media/8d0b81_a11b1d0316b645c589ec9c09369678d8~mv2.png"
    },
    {
      "word": "La toronja",
      "image": "https://static.wixstatic.com/media/8d0b81_8d88b31f18ec43cca3dc36cfbe900ac0~mv2.png"
    },
    {
      "word": "La naranja",
      "image": "https://static.wixstatic.com/media/8d0b81_132d85c61544497fbf03776d30a1af8d~mv2.png"
    },
    {
      "word": "Las frambuesas",
      "image": "https://static.wixstatic.com/media/8d0b81_660d6be4ee264f909106496e5b6dd5ca~mv2.png"
    },
    {
      "word": "La lima",
      "image": "https://static.wixstatic.com/media/8d0b81_cbc88ef8b903422cb00c82f8a8585d64~mv2.png"
    },
    {
      "word": "La sandía",
      "image": "https://static.wixstatic.com/media/8d0b81_d89a3dabb7894b4a822753440b23fc03~mv2.png"
    },
    {
      "word": "La piña",
      "image": "https://static.wixstatic.com/media/8d0b81_2d2ae3cdf7d3428ca3a85bc5f7a85a90~mv2.png"
    },
    {
      "word": "El limón",
      "image": "https://static.wixstatic.com/media/8d0b81_a0afd9fa8fbb450488260d87531204ea~mv2.png"
    },
    {
      "word": "El durazno",
      "image": "https://static.wixstatic.com/media/8d0b81_b6ed47419eac4a869ef1fb09760bb18b~mv2.png"
    },
    {
      "word": "El coco",
      "image": "https://static.wixstatic.com/media/8d0b81_9940bff846034bf7938ff21a5f4be7be~mv2.png"
    },
    {
      "word": "La granada",
      "image": "https://static.wixstatic.com/media/8d0b81_3a8746c5709f45b681443edf8b80bcba~mv2.png"
    },
    {
      "word": "El kiwi",
      "image": "https://static.wixstatic.com/media/8d0b81_4284ab91733949bab558b9043d38f723~mv2.png"
    },
    {
      "word": "Las cerezas",
      "image": "https://static.wixstatic.com/media/8d0b81_75ae3d2e5048488aa6c71208dbf0cacb~mv2.png"
    },
    {
      "word": "Las uvas",
      "image": "https://static.wixstatic.com/media/8d0b81_22548203e6a843ad819432feea214879~mv2.png"
    },
    {
      "word": "El melón",
      "image": "https://static.wixstatic.com/media/8d0b81_d718ef9ef64b42c68e47eb1ee2345343~mv2.png"
    }
  ],
  "Oficios": [
    {
      "word": "El albañil",
      "image": "image/Oficios/El_albañil.png"
    },
    {
      "word": "El carpintero",
      "image": "image/Oficios/El_carpintero.png"
    },
    {
      "word": "El electricista",
      "image": "image/Oficios/El_electricista.png"
    },
    {
      "word": "El fontanero",
      "image": "image/Oficios/El_fontanero.png"
    },
    {
      "word": "El fotógrafo",
      "image": "image/Oficios/El_fotógrafo.png"
    },
    {
      "word": "El guía",
      "image": "image/Oficios/El_guía.png"
    },
    {
      "word": "El jardinero",
      "image": "image/Oficios/El_jardinero.png"
    },
    {
      "word": "El mago",
      "image": "image/Oficios/El_mago.png"
    },
    {
      "word": "El marinero",
      "image": "image/Oficios/El_marinero.png"
    },
    {
      "word": "El militar",
      "image": "image/Oficios/El_militar.png"
    },
    {
      "word": "El oficial de policia",
      "image": "image/Oficios/El_oficial_de_policia.png"
    },
    {
      "word": "El payaso",
      "image": "image/Oficios/El_payaso.png"
    },
    {
      "word": "El trabajador de la construcción",
      "image": "image/Oficios/El_trabajador_de_la_construcción.png"
    },
    {
      "word": "La azafata",
      "image": "image/Oficios/La_azafata.png"
    },
    {
      "word": "La bibliotecaria",
      "image": "image/Oficios/La_bibliotecaria.png"
    },
    {
      "word": "La modelo",
      "image": "image/Oficios/La_modelo.png"
    }
  ],
  "Otoño": [
    {
      "word": "El espantapájaros",
      "image": "image/Otoño/El_espantapájaros.png"
    },
    {
      "word": "Las bellotas",
      "image": "image/Otoño/Las_bellotas.png"
    },
    {
      "word": "Las calabazas",
      "image": "image/Otoño/Las_calabazas.png"
    },
    {
      "word": "Las hojas secas",
      "image": "image/Otoño/Las_hojas_secas.png"
    },
    {
      "word": "Las manzanas",
      "image": "image/Otoño/Las_manzanas.png"
    }
  ],
  "Profesiones": [
    {
      "word": "El arquitecto",
      "image": "image/Profesiones/El_arquitecto.png"
    },
    {
      "word": "El astronauta",
      "image": "image/Profesiones/El_astronauta.png"
    },
    {
      "word": "El atleta",
      "image": "image/Profesiones/El_atleta.png"
    },
    {
      "word": "El bombero",
      "image": "image/Profesiones/El_bombero.png"
    },
    {
      "word": "El cientifico",
      "image": "image/Profesiones/El_cientifico.png"
    },
    {
      "word": "El cirujano",
      "image": "image/Profesiones/El_cirujano.png"
    },
    {
      "word": "El dentista",
      "image": "image/Profesiones/El_dentista.png"
    },
    {
      "word": "El doctor",
      "image": "image/Profesiones/El_doctor.png"
    },
    {
      "word": "El informático",
      "image": "image/Profesiones/El_informático.png"
    },
    {
      "word": "El ingeniero",
      "image": "image/Profesiones/El_ingeniero.png"
    },
    {
      "word": "El músico",
      "image": "image/Profesiones/El_músico.png"
    },
    {
      "word": "El periodista",
      "image": "image/Profesiones/El_periodista.png"
    },
    {
      "word": "El piloto",
      "image": "image/Profesiones/El_piloto.png"
    },
    {
      "word": "El profesor",
      "image": "image/Profesiones/El_profesor.png"
    },
    {
      "word": "El veterinario",
      "image": "image/Profesiones/El_veterinario.png"
    }
  ]
}